tsne_pso/__init__.py
tsne_pso/_tsne_pso.py
tsne_pso/_version.py
tsne_pso/logging_config.py
tsne_pso/py.typed
tsne_pso/tests/__init__.py
tsne_pso/tests/test_tsne_pso.py
tsne_pso-1.1.6.dist-info/licenses/LICENSE
tsne_pso-1.1.6.dist-info/METADATA
tsne_pso-1.1.6.dist-info/WHEEL
tsne_pso-1.1.6.dist-info/top_level.txt
tsne_pso-1.1.6.dist-info/RECORD
