Metadata-Version: 2.4
Name: tsne_pso
Version: 1.1.6
Summary: t-Distributed Stochastic Neighbor Embedding with Particle Swarm Optimization
Home-page: https://github.com/draglesss/t-SNE-PSO
Author: Allaoui, Mebarka, Belhaouari, Samir Brahim, Hedjam, Rachid, Bouanane, Khadra, Kherfi, Mohammed Lamine
Maintainer: Otmane Fatteh
Maintainer-email: Otmane Fatteh <fattehotmane@hotmail.com>
License: BSD-3-Clause
Project-URL: Homepage, https://github.com/draglesss/t-SNE-PSO
Project-URL: Bug Tracker, https://github.com/draglesss/t-SNE-PSO/issues
Project-URL: Documentation, https://github.com/draglesss/t-SNE-PSO#readme
Classifier: Programming Language :: Python :: 3
Classifier: Operating System :: OS Independent
Classifier: Intended Audience :: Science/Research
Classifier: Topic :: Scientific/Engineering :: Artificial Intelligence
Requires-Python: >=3.9
License-File: LICENSE
Requires-Dist: numpy>=1.19.5
Requires-Dist: scipy>=1.6.0
Requires-Dist: scikit-learn>=1.0.0
Requires-Dist: umap-learn>=0.5.3
Requires-Dist: tqdm>=4.64.0
Dynamic: home-page
Dynamic: license-file
Dynamic: maintainer
Dynamic: requires-python
